gold33423307/__init__.py
gold33423307/gold.py
gold33423307-0.0.2.dist-info/LICENSE
gold33423307-0.0.2.dist-info/METADATA
gold33423307-0.0.2.dist-info/WHEEL
gold33423307-0.0.2.dist-info/top_level.txt
gold33423307-0.0.2.dist-info/RECORD
