Metadata-Version: 2.1
Name: gold33423307
Version: 0.0.2
Summary: Simple library to calculate golden ratio
Home-page: https://github.com/KidiXDev/golden_ratio_calculation
Author: KidiXDev
Author-email: <kidixdev@gmail.com>
License: MIT
Keywords: golden_ratio,golden
Classifier: Development Status :: 1 - Planning
License-File: LICENSE
